pqv/__init__.py
pqv/__main__.py
pqv/style.css
pqv-0.9.0.dist-info/licenses/LICENSE
pqv-0.9.0.dist-info/METADATA
pqv-0.9.0.dist-info/WHEEL
pqv-0.9.0.dist-info/entry_points.txt
pqv-0.9.0.dist-info/top_level.txt
pqv-0.9.0.dist-info/RECORD
