Metadata-Version: 2.4
Name: pqv
Version: 0.9.0
Summary: Simple parquet viewer
Home-page: https://github.com/pieterprovoost/pqv
Author: Pieter Provoost
Author-email: pieterprovoost@gmail.com
License: MIT
License-File: LICENSE
Requires-Dist: pyarrow
Requires-Dist: textual
Requires-Dist: pyperclip
Dynamic: author
Dynamic: author-email
Dynamic: home-page
Dynamic: license
Dynamic: license-file
Dynamic: requires-dist
Dynamic: summary
